fppm/__init__.py
fppm/cli/__init__.py
fppm/cli/__main__.py
fppm/cli/config_hooks.py
fppm/cli/router.py
fppm/cli/setup_cli.py
fppm/cli/utils.py
fppm/cli/commands/config.py
fppm/cli/commands/init.py
fppm/cli/commands/install.py
fppm/cli/commands/new.py
fppm/cli/commands/registries.py
fppm/cli/commands/remove.py
fppm/templates/cookiecutter-package/cookiecutter.json
fppm/templates/cookiecutter-package/hooks/pre_gen_project.py
fppm/templates/cookiecutter-package/{{cookiecutter.package_name}}/CMakeLists.txt
fppm/templates/cookiecutter-package/{{cookiecutter.package_name}}/README.md
fppm/templates/cookiecutter-package/{{cookiecutter.package_name}}/library.cmake
fppm/templates/cookiecutter-package/{{cookiecutter.package_name}}/package.yaml
fppm/templates/cookiecutter-package/{{cookiecutter.package_name}}/docs/pdd.md
fppm/templates/cookiecutter-project-yaml/cookiecutter.json
fppm/templates/cookiecutter-project-yaml/TMP_{{cookiecutter.project_name}}/project.yaml
fppm/templates/cookiecutter-project-yaml/hooks/pre_gen_project.py
fprime_fppm-1.1.1.dist-info/LICENSE.txt
fprime_fppm-1.1.1.dist-info/METADATA
fprime_fppm-1.1.1.dist-info/WHEEL
fprime_fppm-1.1.1.dist-info/entry_points.txt
fprime_fppm-1.1.1.dist-info/top_level.txt
fprime_fppm-1.1.1.dist-info/RECORD
