Metadata-Version: 2.1
Name: fprime-fppm
Version: 1.1.1
Summary: A package manager for F Prime
Author-email: Ali Mosallaei <Ali.Mosallaei@jpl.nasa.gov>, Michael Starch <Michael.D.Starch@jpl.nasa.gov>, Thomas Boyer-Chammard <Thomas.Boyer.Chammard@jpl.nasa.gov>
Project-URL: Homepage, https://fprime.jpl.nasa.gov
Project-URL: Documentation, https://github.com/mosa11aei/fprime-fppm/tree/devel/docs
Project-URL: Repository, https://github.com/mosa11aei/fprime-fppm
Keywords: fprime,fppm,nasa,package,flight software
Requires-Python: >=3.8
License-File: LICENSE.txt
Requires-Dist: pyyaml >=6.0.0
Requires-Dist: cookiecutter >=2.2.3
Requires-Dist: validators >=0.28.3
Provides-Extra: test
Requires-Dist: pytest ; extra == 'test'
Requires-Dist: black ; extra == 'test'
